rvpy/__init__.py
rvpy/beta.py
rvpy/binomial.py
rvpy/cauchy.py
rvpy/cuniform.py
rvpy/degenerate.py
rvpy/distribution.py
rvpy/duniform.py
rvpy/f.py
rvpy/gamma.py
rvpy/gompertz.py
rvpy/gumbel.py
rvpy/hypergeom.py
rvpy/laplace.py
rvpy/logistic.py
rvpy/negbin.py
rvpy/normal.py
rvpy/pareto.py
rvpy/poisson.py
rvpy/t.py
rvpy/transformations.py
rvpy/weibull.py
rvpy-0.3.dist-info/LICENSE
rvpy-0.3.dist-info/METADATA
rvpy-0.3.dist-info/WHEEL
rvpy-0.3.dist-info/top_level.txt
rvpy-0.3.dist-info/RECORD
