Metadata-Version: 2.1
Name: rvpy
Version: 0.3
Summary: Working with random variables in an OOish way.
Home-page: https://github.com/timbook/rvpy
Author: Tim Book
Author-email: TimothyKBook@gmail.com
License: MIT
Platform: UNKNOWN
Requires-Dist: numpy
Requires-Dist: sklearn
